monday_async/__init__.py
monday_async/_version.py
monday_async/exceptions.py
monday_async/mondayclient.py
monday_async/core/__init__.py
monday_async/core/client.py
monday_async/core/helpers.py
monday_async/core/response_parser.py
monday_async/graphql/__init__.py
monday_async/graphql/addons.py
monday_async/graphql/mutations/__init__.py
monday_async/graphql/mutations/boards.py
monday_async/graphql/mutations/columns.py
monday_async/graphql/mutations/folders.py
monday_async/graphql/mutations/groups.py
monday_async/graphql/mutations/items.py
monday_async/graphql/mutations/notifications.py
monday_async/graphql/mutations/tag.py
monday_async/graphql/mutations/teams.py
monday_async/graphql/mutations/updates.py
monday_async/graphql/mutations/users.py
monday_async/graphql/mutations/webhook.py
monday_async/graphql/mutations/workspaces.py
monday_async/graphql/queries/__init__.py
monday_async/graphql/queries/account.py
monday_async/graphql/queries/api.py
monday_async/graphql/queries/boards.py
monday_async/graphql/queries/columns.py
monday_async/graphql/queries/complexity.py
monday_async/graphql/queries/folders.py
monday_async/graphql/queries/groups.py
monday_async/graphql/queries/items.py
monday_async/graphql/queries/tag.py
monday_async/graphql/queries/teams.py
monday_async/graphql/queries/updates.py
monday_async/graphql/queries/users.py
monday_async/graphql/queries/webhook.py
monday_async/graphql/queries/workspaces.py
monday_async/resources/__init__.py
monday_async/resources/account.py
monday_async/resources/api.py
monday_async/resources/base_resource.py
monday_async/resources/boards.py
monday_async/resources/columns.py
monday_async/resources/complexity.py
monday_async/resources/custom.py
monday_async/resources/folders.py
monday_async/resources/groups.py
monday_async/resources/items.py
monday_async/resources/notifications.py
monday_async/resources/tags.py
monday_async/resources/teams.py
monday_async/resources/updates.py
monday_async/resources/users.py
monday_async-2.0.0.dist-info/METADATA
monday_async-2.0.0.dist-info/WHEEL
monday_async-2.0.0.dist-info/licenses/LICENSE
monday_async-2.0.0.dist-info/RECORD
